{
  "type": "create:filling",
  "conditions": [
    {
      "type": "forge:and",
      "values": [
        {
          "value": {
            "tag": "forge:plates/constantan",
            "type": "forge:tag_empty"
          },
          "type": "forge:not"
        },
        {
          "type": "forge:mod_loaded",
          "modid": "tconstruct"
        }
      ]
    }
  ],
  "ingredients": [
    {
      "tag": "tconstruct:casts/single_use/plate"
    },
    {
      "fluid": "tconstruct:molten_constantan",
      "nbt": {},
      "amount": 144
    }
  ],
  "results": [
    {
      "tag": "forge:plates/constantan"
    }
  ]
}