{
  "conditions": [
    {
      "type": "forge:and",
      "values": [
        {
          "type": "forge:mod_loaded",
          "modid": "kubejs"
        },
        {
          "type": "forge:mod_loaded",
          "modid": "neapolitan"
        }
      ]
    }
  ],
  "type": "create:emptying",
  "ingredients": [
    {
      "item": "neapolitan:mint_milkshake"
    }
  ],
  "results": [
    {
      "item": "minecraft:glass_bottle"
    },
    {
      "fluid": "kubejs:mint_milkshake",
      "nbt": {},
      "amount": 250
    }
  ]
}